pipatch/__init__.py
pipatch/pipatch.py
pipatch-0.1.1.dist-info/LICENSE
pipatch-0.1.1.dist-info/METADATA
pipatch-0.1.1.dist-info/WHEEL
pipatch-0.1.1.dist-info/top_level.txt
pipatch-0.1.1.dist-info/RECORD
